eqo/__init__.py
eqo/__main__.py
eqo/eqocom.py
eqo/qubo/__init__.py
eqo/qubo/analyze.py
eqo/qubo/markov.py
eqo/qubo/packedqubo.py
eqo/qubo/qubo.py
eqo/qubo/qubotools.py
eqo/qubo/stackedqubo.py
eqo/qubo/visualize.py
eqo-0.3.dist-info/LICENSE.md
eqo-0.3.dist-info/METADATA
eqo-0.3.dist-info/WHEEL
eqo-0.3.dist-info/top_level.txt
eqo-0.3.dist-info/RECORD
